mopidy_snapduck/__init__.py
mopidy_snapduck/ext.conf
mopidy_snapduck/frontend.py
Mopidy_Snapduck-1.0.0.dist-info/LICENSE
Mopidy_Snapduck-1.0.0.dist-info/METADATA
Mopidy_Snapduck-1.0.0.dist-info/WHEEL
Mopidy_Snapduck-1.0.0.dist-info/entry_points.txt
Mopidy_Snapduck-1.0.0.dist-info/top_level.txt
Mopidy_Snapduck-1.0.0.dist-info/RECORD
