Metadata-Version: 2.1
Name: Mopidy-Snapduck
Version: 1.0.0
Summary: Mopidy extension for controlling a local Snapcast client
Home-page: https://github.com/daniele-athome/mopidy-snapduck
Author: Daniele Ricci
Author-email: daniele+pypi@casaricci.it
License: GPLv3
Project-URL: Source, https://github.com/daniele-athome/mopidy-snapduck
Project-URL: Issues, https://github.com/daniele-athome/mopidy-snapduck/issues
Platform: UNKNOWN
Classifier: Environment :: No Input/Output (Daemon)
Classifier: Intended Audience :: End Users/Desktop
Classifier: License :: OSI Approved :: GNU General Public License v3 or later (GPLv3+)
Classifier: Operating System :: OS Independent
Classifier: Programming Language :: Python :: 3
Classifier: Programming Language :: Python :: 3.7
Classifier: Programming Language :: Python :: 3.8
Classifier: Programming Language :: Python :: 3.9
Classifier: Topic :: Multimedia :: Sound/Audio :: Players
Requires-Python: >=3.7
Requires-Dist: Mopidy (>=3.0.0)
Requires-Dist: Pykka (>=2.0.1)
Requires-Dist: setuptools
Provides-Extra: dev
Requires-Dist: check-manifest ; extra == 'dev'
Requires-Dist: flake8 ; extra == 'dev'
Requires-Dist: flake8-bugbear ; extra == 'dev'
Requires-Dist: flake8-import-order ; extra == 'dev'
Requires-Dist: isort[pyproject] ; extra == 'dev'
Requires-Dist: pytest ; extra == 'dev'
Requires-Dist: pytest-cov ; extra == 'dev'
Provides-Extra: lint
Requires-Dist: check-manifest ; extra == 'lint'
Requires-Dist: flake8 ; extra == 'lint'
Requires-Dist: flake8-bugbear ; extra == 'lint'
Requires-Dist: flake8-import-order ; extra == 'lint'
Requires-Dist: isort[pyproject] ; extra == 'lint'
Provides-Extra: test
Requires-Dist: pytest ; extra == 'test'
Requires-Dist: pytest-cov ; extra == 'test'
